cslib/__init__.py
cslib/algorithms/__init__.py
cslib/algorithms/object_proposals.py
cslib/algorithms/pytorch_msssim.py
cslib/algorithms/msd/__init__.py
cslib/algorithms/msd/base.py
cslib/algorithms/msd/contrust.py
cslib/algorithms/msd/fsd.py
cslib/algorithms/msd/graident.py
cslib/algorithms/msd/laplacian.py
cslib/algorithms/msd/morphological.py
cslib/algorithms/msd/steerable.py
cslib/datasets/__init__.py
cslib/datasets/classification.py
cslib/datasets/detection.py
cslib/datasets/fusion.py
cslib/datasets/image.py
cslib/datasets/linear.py
cslib/datasets/sr.py
cslib/datasets/collection/__init__.py
cslib/datasets/collection/flowers17.py
cslib/datasets/collection/fmb.py
cslib/datasets/collection/general_detection.py
cslib/datasets/collection/general_fusion.py
cslib/datasets/collection/general_sr.py
cslib/datasets/collection/imagenetval.py
cslib/datasets/collection/ino.py
cslib/datasets/collection/llvip.py
cslib/datasets/collection/m3fd.py
cslib/datasets/collection/msrs.py
cslib/datasets/collection/roadscene.py
cslib/datasets/collection/tinyimagenet.py
cslib/datasets/collection/tno.py
cslib/deprecated/__init__.py
cslib/deprecated/projects/__init__.py
cslib/deprecated/projects/classical.py
cslib/deprecated/projects/classify.py
cslib/deprecated/projects/fusion.py
cslib/deprecated/projects/gan.py
cslib/deprecated/projects/parts.py
cslib/deprecated/projects/sr.py
cslib/deprecated/projects/collection/__init__.py
cslib/deprecated/projects/collection/AUIF/__init__.py
cslib/deprecated/projects/collection/AUIF/config.py
cslib/deprecated/projects/collection/AUIF/inference.py
cslib/deprecated/projects/collection/AUIF/model.py
cslib/deprecated/projects/collection/AUIF/utils.py
cslib/deprecated/projects/collection/CDDFuse/__init__.py
cslib/deprecated/projects/collection/CDDFuse/config.py
cslib/deprecated/projects/collection/CDDFuse/inference.py
cslib/deprecated/projects/collection/CDDFuse/model.py
cslib/deprecated/projects/collection/CDDFuse/utils.py
cslib-0.3.0.dist-info/METADATA
cslib-0.3.0.dist-info/WHEEL
cslib-0.3.0.dist-info/entry_points.txt
cslib-0.3.0.dist-info/licenses/LICENSE
cslib-0.3.0.dist-info/RECORD
