Metadata-Version: 2.4
Name: cslib
Version: 0.3.0
Summary: AI Lab of Charles Shan -- A Notebook for AI Learning
Author-email: Charles Shan <charles.shht@gmail.com>
License-File: LICENSE
Requires-Python: >=3.12
Requires-Dist: albumentations
Requires-Dist: click
Requires-Dist: einops
Requires-Dist: kornia
Requires-Dist: matplotlib
Requires-Dist: pycocotools
Requires-Dist: scikit-image
Requires-Dist: scikit-learn
Requires-Dist: seaborn
Requires-Dist: tensorboard
Requires-Dist: timm
Requires-Dist: torch>=2.0.0
Requires-Dist: torchmetrics
Requires-Dist: torchvision
Requires-Dist: tqdm
Requires-Dist: twine>=6.1.0
Requires-Dist: visdom
Requires-Dist: wandb
